zetops/zetmiko/__init__.py
zetops/zetmiko/fiberhome/__init__.py
zetops/zetmiko/fiberhome/fiberhome_ssh.py
zetops/zetmiko/hillstone/__init__.py
zetops/zetmiko/hillstone/hillstone_ssh.py
zetops/zetmiko/huawei/__init__.py
zetops/zetmiko/huawei/huawei.py
zetops/zetmiko/mypower/__init__.py
zetops/zetmiko/mypower/mypower.py
zetops/zetmiko/ssh_dispatcher.py
zetops-0.1.8.dist-info/WHEEL
zetops-0.1.8.dist-info/METADATA
zetops-0.1.8.dist-info/RECORD
