Metadata-Version: 2.1
Name: zetops
Version: 0.1.8
Summary: A NetDevOps package aiming to improve NetDevOps(network automation) development efficiency for network development engineer!
Home-page: https://github.com/jiujing/zetops
License:  LGPL
Keywords: NetDevOps,nornir,netmiko,network,sre,automation,devops
Author: feifeiflight
Author-email: feifeiflight@126.com
Classifier: License :: OSI Approved :: Apache Software License
Classifier: License :: Other/Proprietary License
Classifier: Programming Language :: Python :: 2
Classifier: Programming Language :: Python :: 2.7
Classifier: Programming Language :: Python :: 3
Classifier: Programming Language :: Python :: 3.4
Classifier: Programming Language :: Python :: 3.5
Classifier: Programming Language :: Python :: 3.6
Classifier: Programming Language :: Python :: 3.7
Classifier: Programming Language :: Python :: 3.8
Classifier: Programming Language :: Python :: 3.9
Classifier: Programming Language :: Python :: 3.10
Classifier: Programming Language :: Python :: 3.11
Classifier: Programming Language :: Python :: 3
Classifier: Programming Language :: Python :: 3.10
Classifier: Programming Language :: Python :: 3.6
Classifier: Programming Language :: Python :: 3.7
Classifier: Programming Language :: Python :: 3.8
Classifier: Programming Language :: Python :: 3.9
Classifier: Topic :: System :: Networking
Project-URL: Repository, https://github.com/jiujing/zetops
